{
  "timestamp": "2026-01-06T21:41:16.518Z",
  "analysis": {
    "file": "server.js",
    "language": "javascript",
    "totalComments": 20,
    "totalLines": 201,
    "commentRatio": 0.09950248756218906,
    "quality": {
      "clarity": 0,
      "completeness": 0,
      "relevance": 0,
      "style": 40,
      "placement": 0
    },
    "issues": [
      {
        "type": "style",
        "severity": "warning",
        "message": "Comment exceeds recommended length (1137/100)",
        "line": 1
      },
      {
        "type": "style",
        "severity": "warning",
        "message": "Comment exceeds recommended length (1134/100)",
        "line": 1
      },
      {
        "type": "relevance",
        "severity": "info",
        "message": "Comment may be redundant with code",
        "line": 41
      },
      {
        "type": "relevance",
        "severity": "info",
        "message": "Comment may be redundant with code",
        "line": 53
      },
      {
        "type": "relevance",
        "severity": "info",
        "message": "Comment may be redundant with code",
        "line": 67
      },
      {
        "type": "relevance",
        "severity": "info",
        "message": "Comment may be redundant with code",
        "line": 71
      },
      {
        "type": "relevance",
        "severity": "info",
        "message": "Comment may be redundant with code",
        "line": 91
      },
      {
        "type": "relevance",
        "severity": "info",
        "message": "Comment may be redundant with code",
        "line": 99
      },
      {
        "type": "relevance",
        "severity": "info",
        "message": "Comment may be redundant with code",
        "line": 102
      },
      {
        "type": "relevance",
        "severity": "info",
        "message": "Comment may be redundant with code",
        "line": 125
      },
      {
        "type": "relevance",
        "severity": "info",
        "message": "Comment may be redundant with code",
        "line": 144
      },
      {
        "type": "relevance",
        "severity": "info",
        "message": "Comment may be redundant with code",
        "line": 157
      },
      {
        "type": "relevance",
        "severity": "info",
        "message": "Comment may be redundant with code",
        "line": 166
      },
      {
        "type": "relevance",
        "severity": "info",
        "message": "Comment may be redundant with code",
        "line": 177
      },
      {
        "type": "relevance",
        "severity": "info",
        "message": "Comment may be redundant with code",
        "line": 180
      },
      {
        "type": "relevance",
        "severity": "info",
        "message": "Comment may be redundant with code",
        "line": 185
      },
      {
        "type": "relevance",
        "severity": "info",
        "message": "Comment may be redundant with code",
        "line": 194
      }
    ],
    "suggestions": [
      "Break long comments into multiple lines or shorten",
      "Start comments with capital letters for better readability",
      "End comments with proper punctuation",
      "Consider using JSDoc format for function comments",
      "Break long comments into multiple lines or shorten",
      "Start comments with capital letters for better readability",
      "End comments with proper punctuation",
      "Consider adding action-oriented language",
      "Consider explaining why this code exists, not just what it does",
      "Remove redundant comments that just restate the code",
      "End comments with proper punctuation",
      "Consider using JSDoc format for function comments",
      "Avoid stacking single-line comments; use multi-line format",
      "Consider adding action-oriented language",
      "Remove redundant comments that just restate the code",
      "End comments with proper punctuation",
      "Consider using JSDoc format for function comments",
      "Avoid stacking single-line comments; use multi-line format",
      "Consider adding action-oriented language",
      "Remove redundant comments that just restate the code",
      "End comments with proper punctuation",
      "Consider using JSDoc format for function comments",
      "Avoid stacking single-line comments; use multi-line format",
      "Consider adding action-oriented language",
      "Consider explaining why this code exists, not just what it does",
      "Remove redundant comments that just restate the code",
      "End comments with proper punctuation",
      "Consider using JSDoc format for function comments",
      "Avoid stacking single-line comments; use multi-line format",
      "Consider adding action-oriented language",
      "Consider explaining why this code exists, not just what it does",
      "End comments with proper punctuation",
      "Consider using JSDoc format for function comments",
      "Consider adding action-oriented language",
      "End comments with proper punctuation",
      "Consider using JSDoc format for function comments",
      "Consider adding action-oriented language",
      "Consider explaining why this code exists, not just what it does",
      "Remove redundant comments that just restate the code",
      "End comments with proper punctuation",
      "Consider using JSDoc format for function comments",
      "Avoid stacking single-line comments; use multi-line format",
      "Consider adding action-oriented language",
      "Consider explaining why this code exists, not just what it does",
      "Remove redundant comments that just restate the code",
      "End comments with proper punctuation",
      "Consider using JSDoc format for function comments",
      "Avoid stacking single-line comments; use multi-line format",
      "Consider adding action-oriented language",
      "Consider explaining why this code exists, not just what it does",
      "Remove redundant comments that just restate the code",
      "Consider using JSDoc format for function comments",
      "Avoid stacking single-line comments; use multi-line format",
      "Consider adding action-oriented language",
      "Consider explaining why this code exists, not just what it does",
      "Consider using JSDoc format for function comments",
      "Consider adding action-oriented language",
      "Consider explaining why this code exists, not just what it does",
      "Remove redundant comments that just restate the code",
      "End comments with proper punctuation",
      "Consider using JSDoc format for function comments",
      "Avoid stacking single-line comments; use multi-line format",
      "Consider adding action-oriented language",
      "Remove redundant comments that just restate the code",
      "End comments with proper punctuation",
      "Consider using JSDoc format for function comments",
      "Avoid stacking single-line comments; use multi-line format",
      "Consider adding action-oriented language",
      "Consider explaining why this code exists, not just what it does",
      "Remove redundant comments that just restate the code",
      "End comments with proper punctuation",
      "Consider using JSDoc format for function comments",
      "Avoid stacking single-line comments; use multi-line format",
      "Consider adding action-oriented language",
      "Consider explaining why this code exists, not just what it does",
      "Remove redundant comments that just restate the code",
      "End comments with proper punctuation",
      "Consider using JSDoc format for function comments",
      "Avoid stacking single-line comments; use multi-line format",
      "Consider adding action-oriented language",
      "Consider explaining why this code exists, not just what it does",
      "Remove redundant comments that just restate the code",
      "End comments with proper punctuation",
      "Consider using JSDoc format for function comments",
      "Avoid stacking single-line comments; use multi-line format",
      "Consider adding action-oriented language",
      "Remove redundant comments that just restate the code",
      "End comments with proper punctuation",
      "Consider using JSDoc format for function comments",
      "Avoid stacking single-line comments; use multi-line format",
      "Consider adding action-oriented language",
      "Consider explaining why this code exists, not just what it does",
      "Remove redundant comments that just restate the code",
      "End comments with proper punctuation",
      "Consider using JSDoc format for function comments",
      "Avoid stacking single-line comments; use multi-line format",
      "Consider adding action-oriented language",
      "Consider explaining why this code exists, not just what it does",
      "Remove redundant comments that just restate the code",
      "End comments with proper punctuation",
      "Consider using JSDoc format for function comments",
      "Avoid stacking single-line comments; use multi-line format"
    ],
    "breakdown": {
      "byType": {
        "multiLine": 1,
        "jsdoc": 1,
        "singleLine": 18
      },
      "byLength": {
        "short": 0,
        "medium": 11,
        "long": 9
      },
      "byQuality": {
        "good": 0,
        "fair": 20,
        "poor": 0
      }
    },
    "score": 38
  },
  "recommendations": [
    "Use JSDoc format for function and class documentation"
  ]
}